{
  "spec": {
    "num_qubits": 5,
    "topology": "triangulated",
    "custom_edges": "0-1:1.0000,0-2:0.9585,0-3:1.0000,0-4:1.0000,1-2:0.9298,1-3:0.9298,1-4:1.0000,2-3:1.0000,2-4:0.8592,3-4:1.0000",
    "alpha": 0.1,
    "weight": 1.0,
    "gamma": 0.3,
    "sigma": null,
    "init_angle": 0.0,
    "init_angles": null,
    "shots": 1000,
    "device": "ibm_brisbane",
    "geometry": "hyperbolic",
    "curvature": 3.0,
    "timesteps": 1,
    "dimension": 2,
    "mass_hinge": null,
    "mass_value": 0.0,
    "solve_regge": false,
    "lorentzian": false,
    "excite": false,
    "fast": false,
    "strong_curvature": false,
    "charge_injection": false,
    "charge_strength": 1.0,
    "charge_location": 3,
    "spin_injection": false,
    "spin_strength": 1.0,
    "spin_location": 3
  },
  "uid": "R7K50J",
  "counts_per_timestep": [
    null
  ],
  "job_ids_per_timestep": [
    "d20od8jni11c73fct0fg"
  ],
  "entropy_per_timestep": [
    null
  ],
  "mutual_information_per_timestep": [
    {
      "I_0,1": 0.1,
      "I_0,2": 0.1,
      "I_0,3": 0.1,
      "I_0,4": 0.1,
      "I_1,2": 0.1,
      "I_1,3": 0.1,
      "I_1,4": 0.1,
      "I_2,3": 0.1,
      "I_2,4": 0.1,
      "I_3,4": 0.1
    }
  ],
  "distance_matrix_per_timestep": [
    [
      [
        0.0,
        2.0,
        2.0,
        2.0,
        2.0
      ],
      [
        2.0,
        0.0,
        2.0,
        2.0,
        2.0
      ],
      [
        2.0,
        2.0,
        0.0,
        2.0,
        2.0
      ],
      [
        2.0,
        2.0,
        2.0,
        0.0,
        2.0
      ],
      [
        2.0,
        2.0,
        2.0,
        2.0,
        0.0
      ]
    ]
  ],
  "edge_mi": {
    "0,1": 0.1,
    "0,4": 0.1,
    "0,2": 0.1,
    "1,2": 0.1,
    "1,4": 0.1,
    "2,3": 0.1,
    "2,4": 0.1,
    "3,4": 0.1
  },
  "distance_matrix": [
    [
      0.0,
      2.3025850929940455,
      2.3025850929940455,
      2.3025850929940455,
      2.3025850929940455
    ],
    [
      2.3025850929940455,
      0.0,
      2.3025850929940455,
      2.3025850929940455,
      2.3025850929940455
    ],
    [
      2.3025850929940455,
      2.3025850929940455,
      0.0,
      2.3025850929940455,
      2.3025850929940455
    ],
    [
      2.3025850929940455,
      2.3025850929940455,
      2.3025850929940455,
      0.0,
      2.3025850929940455
    ],
    [
      2.3025850929940455,
      2.3025850929940455,
      2.3025850929940455,
      2.3025850929940455,
      0.0
    ]
  ],
  "shortest_paths": {
    "0": {
      "0": 0,
      "1": 2.3025850929940455,
      "2": 2.3025850929940455,
      "3": 2.3025850929940455,
      "4": 2.3025850929940455
    },
    "1": {
      "1": 0,
      "0": 2.3025850929940455,
      "2": 2.3025850929940455,
      "3": 2.3025850929940455,
      "4": 2.3025850929940455
    },
    "2": {
      "2": 0,
      "0": 2.3025850929940455,
      "1": 2.3025850929940455,
      "3": 2.3025850929940455,
      "4": 2.3025850929940455
    },
    "3": {
      "3": 0,
      "0": 2.3025850929940455,
      "1": 2.3025850929940455,
      "2": 2.3025850929940455,
      "4": 2.3025850929940455
    },
    "4": {
      "4": 0,
      "0": 2.3025850929940455,
      "1": 2.3025850929940455,
      "2": 2.3025850929940455,
      "3": 2.3025850929940455
    }
  },
  "gromov_delta": 1.1512925464970227,
  "mean_distance": 1.8420680743952362,
  "angle_sums": [
    0.8043634593045942,
    0.8043634593045942,
    0.8043634593045942,
    0.8043634593045942,
    0.8043634593045942,
    0.8043634593045942,
    0.8043634593045942,
    0.8043634593045942,
    0.8043634593045942,
    0.8043634593045942
  ],
  "mean_angle_sum": 0.8043634593045942,
  "min_angle_sum": 0.8043634593045942,
  "max_angle_sum": 0.8043634593045942,
  "angle_sum_deviations": [
    -2.337229194285199,
    -2.337229194285199,
    -2.337229194285199,
    -2.337229194285199,
    -2.337229194285199,
    -2.337229194285199,
    -2.337229194285199,
    -2.337229194285199,
    -2.337229194285199,
    -2.337229194285199
  ],
  "triangle_inequality_violations": [],
  "embedding_coords": [
    [
      -7.269219555936899,
      6.257995564658831
    ],
    [
      9.56674693789476,
      -0.7847043596663439
    ],
    [
      -8.191210902731255,
      -4.986297232977488
    ],
    [
      3.6915513191829827,
      8.828609852508007
    ],
    [
      2.202132201590414,
      -9.315603824523006
    ]
  ],
  "embedding_coords_3d": [
    [
      -5.844127573652303,
      -0.12325805433911333,
      7.690329796706355
    ],
    [
      6.89927051390893,
      -4.661479856787774,
      5.231656263798897
    ],
    [
      -6.7750308070353675,
      -4.9375485330368045,
      -5.136170451624813
    ],
    [
      -0.1073146159927334,
      9.847608686557853,
      -0.0826865307063566
    ],
    [
      5.827202482771472,
      -0.12532224239416254,
      -7.703129078174084
    ]
  ],
  "edge_weight_variance": 0.002098944100000001,
  "event_nodes": [
    [
      0,
      0
    ],
    [
      1,
      0
    ],
    [
      2,
      0
    ],
    [
      3,
      0
    ],
    [
      4,
      0
    ]
  ],
  "event_edges": [
    {
      "type": "spatial",
      "from": [
        0,
        0
      ],
      "to": [
        1,
        0
      ],
      "weight": 2.3025850929940455
    },
    {
      "type": "spatial",
      "from": [
        0,
        0
      ],
      "to": [
        2,
        0
      ],
      "weight": 2.3025850929940455
    },
    {
      "type": "spatial",
      "from": [
        0,
        0
      ],
      "to": [
        3,
        0
      ],
      "weight": 4.605170185988091
    },
    {
      "type": "spatial",
      "from": [
        0,
        0
      ],
      "to": [
        4,
        0
      ],
      "weight": 2.3025850929940455
    },
    {
      "type": "spatial",
      "from": [
        1,
        0
      ],
      "to": [
        2,
        0
      ],
      "weight": 2.3025850929940455
    },
    {
      "type": "spatial",
      "from": [
        1,
        0
      ],
      "to": [
        3,
        0
      ],
      "weight": 4.605170185988091
    },
    {
      "type": "spatial",
      "from": [
        1,
        0
      ],
      "to": [
        4,
        0
      ],
      "weight": 2.3025850929940455
    },
    {
      "type": "spatial",
      "from": [
        2,
        0
      ],
      "to": [
        3,
        0
      ],
      "weight": 2.3025850929940455
    },
    {
      "type": "spatial",
      "from": [
        2,
        0
      ],
      "to": [
        4,
        0
      ],
      "weight": 2.3025850929940455
    },
    {
      "type": "spatial",
      "from": [
        3,
        0
      ],
      "to": [
        4,
        0
      ],
      "weight": 2.3025850929940455
    }
  ],
  "lorentzian_dissimilarity": [
    [
      0.0,
      5.301898110478397,
      5.301898110478397,
      21.207592441913587,
      5.301898110478397
    ],
    [
      5.301898110478397,
      0.0,
      5.301898110478397,
      21.207592441913587,
      5.301898110478397
    ],
    [
      5.301898110478397,
      5.301898110478397,
      0.0,
      5.301898110478397,
      5.301898110478397
    ],
    [
      21.207592441913587,
      21.207592441913587,
      5.301898110478397,
      0.0,
      5.301898110478397
    ],
    [
      5.301898110478397,
      5.301898110478397,
      5.301898110478397,
      5.301898110478397,
      0.0
    ]
  ],
  "lorentzian_embedding": [
    [
      0.0,
      -1.5166041126145349,
      0.43108230123063507
    ],
    [
      0.0,
      -0.5546612919159205,
      2.1328594202526783
    ],
    [
      0.0,
      1.1466707335788922,
      0.936135021278738
    ],
    [
      0.0,
      2.833506591763289,
      -0.9050871776046966
    ],
    [
      0.0,
      0.3861020047989845,
      -0.4093935894897565
    ]
  ],
  "edge_length_evolution": [],
  "angle_deficit_evolution": [],
  "regge_action_evolution": [],
  "gromov_delta_evolution": [],
  "mass_hinge": null,
  "mass_value": 0.0,
  "matter": {
    "(0, 1)": 0.0,
    "(2, 4)": 0.0,
    "(1, 2)": 0.0,
    "(0, 4)": 0.0,
    "(3, 4)": 0.0,
    "(0, 3)": 0.0,
    "(1, 4)": 0.0,
    "(2, 3)": 0.0,
    "(0, 2)": 0.0,
    "(1, 3)": 0.0
  },
  "stationary_solution": null,
  "bootstrap_analysis": {
    "gromov_delta": {
      "mean": 1.0,
      "lower_ci": 1.0,
      "upper_ci": 1.0,
      "all_values": [
        1.0
      ],
      "uncertainty": 0.0
    },
    "entropy": {
      "mean": null,
      "lower_ci": null,
      "upper_ci": null,
      "uncertainty": null
    },
    "distance_matrix": {
      "mean": [
        [
          0.0,
          2.0,
          2.0,
          2.0,
          2.0
        ],
        [
          2.0,
          0.0,
          2.0,
          2.0,
          2.0
        ],
        [
          2.0,
          2.0,
          0.0,
          2.0,
          2.0
        ],
        [
          2.0,
          2.0,
          2.0,
          0.0,
          2.0
        ],
        [
          2.0,
          2.0,
          2.0,
          2.0,
          0.0
        ]
      ],
      "lower_ci": [
        [
          0.0,
          2.0,
          2.0,
          2.0,
          2.0
        ],
        [
          2.0,
          0.0,
          2.0,
          2.0,
          2.0
        ],
        [
          2.0,
          2.0,
          0.0,
          2.0,
          2.0
        ],
        [
          2.0,
          2.0,
          2.0,
          0.0,
          2.0
        ],
        [
          2.0,
          2.0,
          2.0,
          2.0,
          0.0
        ]
      ],
      "upper_ci": [
        [
          0.0,
          2.0,
          2.0,
          2.0,
          2.0
        ],
        [
          2.0,
          0.0,
          2.0,
          2.0,
          2.0
        ],
        [
          2.0,
          2.0,
          0.0,
          2.0,
          2.0
        ],
        [
          2.0,
          2.0,
          2.0,
          0.0,
          2.0
        ],
        [
          2.0,
          2.0,
          2.0,
          2.0,
          0.0
        ]
      ]
    }
  },
  "topology_compatibility": {
    "current_topology": "triangulated",
    "explanation": "Triangulated topology is specifically designed for angle-sum curvature. Creates multiple triangles per vertex, enabling robust local curvature measurements. Each vertex has multiple incident triangles for well-defined angle sums.",
    "supports_local_curvature": true
  },
  "rt_surface_analysis": {
    "boundary_A": [
      0,
      1,
      2
    ],
    "boundary_B": [
      3,
      4,
      5,
      6
    ],
    "bulk_point": 3,
    "rt_area_A": 6.0,
    "rt_area_B": 2.0,
    "rt_area_ratio": 0.3333333333333333,
    "edge_lengths": [
      2.0,
      2.0,
      2.0,
      2.0,
      2.0,
      2.0,
      2.0,
      2.0,
      2.0,
      2.0
    ],
    "all_edges": [
      [
        0,
        1
      ],
      [
        0,
        2
      ],
      [
        0,
        3
      ],
      [
        0,
        4
      ],
      [
        1,
        2
      ],
      [
        1,
        3
      ],
      [
        1,
        4
      ],
      [
        2,
        3
      ],
      [
        2,
        4
      ],
      [
        3,
        4
      ]
    ]
  },
  "bulk_excitation_analysis": null,
  "dynamic_evidence": {
    "angle_sums_per_timestep": [
      [
        3.141592653589793,
        3.141592653589793,
        3.141592653589793,
        3.141592653589793,
        3.141592653589793,
        3.141592653589793,
        3.141592653589793,
        3.141592653589793,
        3.141592653589793,
        3.141592653589793,
        3.141592653589793,
        3.141592653589793,
        3.141592653589793,
        3.141592653589793,
        3.141592653589793,
        3.141592653589793,
        3.141592653589793,
        3.141592653589793,
        3.141592653589793,
        3.141592653589793,
        3.141592653589793,
        3.141592653589793,
        3.141592653589793,
        3.141592653589793,
        3.141592653589793,
        3.141592653589793,
        3.141592653589793,
        3.141592653589793,
        3.141592653589793,
        3.141592653589793,
        3.141592653589793,
        3.141592653589793,
        3.141592653589793,
        3.141592653589793,
        3.141592653589793
      ]
    ],
    "gromov_delta_per_timestep": [
      0.5
    ],
    "edge_mi_per_timestep": [
      {}
    ],
    "shortest_paths_per_timestep": [
      {}
    ],
    "mean_distance_per_timestep": [
      2.0
    ],
    "triangle_violations_per_timestep": [
      0
    ],
    "embedding_coords_per_timestep": [
      null
    ],
    "regge_evolution_data": null,
    "evolution_summary": {
      "total_timesteps": 1,
      "gromov_delta_range": [
        0.5,
        0.5
      ],
      "mean_distance_range": [
        2.0,
        2.0
      ],
      "total_triangle_violations": 0,
      "hyperbolic_evolution": [
        false
      ],
      "regge_corrected": false
    }
  }
}